README.md
setup.py
literate_vim/__init__.py
literate_vim/__main__.py
literate_vim.egg-info/PKG-INFO
literate_vim.egg-info/SOURCES.txt
literate_vim.egg-info/dependency_links.txt
literate_vim.egg-info/entry_points.txt
literate_vim.egg-info/requires.txt
literate_vim.egg-info/top_level.txt