Metadata-Version: 2.1
Name: literate-vim
Version: 0.1
Summary: Literate vim configuration.
Home-page: https://gitlab.com/joajfreitas/literate-vim
Author: Joao Freitas
Author-email: joaj.freitas@gmail.com
License: GPLv3
Platform: UNKNOWN
